{"index.md":"fea31d21","其他_js手写题.md":"be003057","其他_插件.md":"974ccca7","其他_问题.md":"39082963","原生_css相关_css属性.md":"61481ac8","原生_css相关_创意构想.md":"fd436fa3","原生_js相关_proxy.md":"9901b3f9","原生_js相关_js api.md":"2520b2d3","原生_js相关_promise.md":"65c8c42e","原生_js相关_设计模式.md":"b734a44a","原生_ts相关_typescript.md":"7a23b388","构建工具_pnpm-workspace搭建项目.md":"dca585d9","构建工具_rollup.md":"9c34d5ee","构建工具_vite.md":"7b11b9e6","构建工具_webpack5.74.0.md":"a6dda4b0","生态_electron_开始.md":"12fc61cb","生态_electron_问题.md":"5b113a0b","生态_konva_开始.md":"f6146629","生态_nestjs_nestjs.md":"b474c63a","生态_pixi_开始.md":"3bf69ee2","生态_react_vite_react项目.md":"27daf23d","生态_three_index.md":"d116fc63","生态_vue_vue2和vue3的区别.md":"d717c5a6","生态_vue_vue3使用工具.md":"98b53b1b","生态_vue_开始.md":"46ec6e55","面试题_javascript_javascript(一).md":"339385bb","面试题_vue_vue响应式简易实现.md":"6bd5b4b9","面试题_vue_vue面试题.md":"36e77632","面试题_源码_promise.md":"a687ce5e","面试题_面试题.md":"1ff8f804"}
